ffmpeg_splitter.py
py_ffmpeg_splitter-0.0.3.dist-info/LICENSE
py_ffmpeg_splitter-0.0.3.dist-info/METADATA
py_ffmpeg_splitter-0.0.3.dist-info/WHEEL
py_ffmpeg_splitter-0.0.3.dist-info/top_level.txt
py_ffmpeg_splitter-0.0.3.dist-info/RECORD
