Metadata-Version: 2.1
Name: py_ffmpeg_splitter
Version: 0.0.3
Summary: A simple python library used to split media files.
Author-email: Sahar Shulman <dillpickledev@gmail.com>
Project-URL: Homepage, https://github.com/hohfchns/py-ffmpeg-splitter
Project-URL: Issues, https://github.com/hohfchns/py-ffmpeg-splitter/issues
Classifier: Programming Language :: Python :: 3
Classifier: License :: OSI Approved :: BSD License
Classifier: Operating System :: OS Independent
Requires-Python: >=3.6
License-File: LICENSE
Requires-Dist: plac
